sketch_bbmh.cpython-39-darwin.so
sketch_bf.cpython-39-darwin.so
sketch_hll.cpython-39-darwin.so
sketch_hmh.cpython-39-darwin.so
sketch_lsh.cpython-39-darwin.so
sketch_ss.cpython-39-darwin.so
sketch_util.cpython-39-darwin.so
sketch_ds/__init__.py
sketch_ds/sketch_test.py
sketch_ds-0.19.0.dist-info/LICENSE
sketch_ds-0.19.0.dist-info/METADATA
sketch_ds-0.19.0.dist-info/WHEEL
sketch_ds-0.19.0.dist-info/top_level.txt
sketch_ds-0.19.0.dist-info/RECORD
