Metadata-Version: 2.1
Name: sketch-ds
Version: 0.19.0
Summary: A Python module for constructing and comparing sketch data structures
Home-page: https://github.com/dnbaker/sketch
Author: Daniel Baker
Author-email: Daniel Baker <dnb@cs.jhu.edu>
Project-URL: Homepage, https://github.com/dnbaker/sketch
Project-URL: Bug Tracker, https://github.com/dnbaker/sketch/issues
Classifier: Programming Language :: Python :: 3
Classifier: License :: OSI Approved :: MIT License
Classifier: Operating System :: OS Independent
Requires-Python: >=3.5
License-File: LICENSE
